pylatinize/__init__.py
pylatinize/core.py
pylatinize/mappings.py
pylatinize-0.0.1.dist-info/licenses/LICENSE
pylatinize-0.0.1.dist-info/METADATA
pylatinize-0.0.1.dist-info/WHEEL
pylatinize-0.0.1.dist-info/top_level.txt
pylatinize-0.0.1.dist-info/RECORD
