Metadata-Version: 2.4
Name: pylatinize
Version: 0.0.1
Summary: A lightweight, Open Source Python library for transliterating and normalizing Unicode text to Latin ASCII using configurable mappings and Unicode normalization forms, written in Python.
Author-email: Zsolt Oroszlány <hello@playfulsparkle.com>
Maintainer-email: Zsolt Oroszlány <hello@playfulsparkle.com>
License: BSD-3-Clause
Project-URL: Bug Tracker, https://github.com/playfulsparkle/pylatinize/issues
Project-URL: Change Log, https://github.com/playfulsparkle/pylatinize/blob/main/CHANGELOG.md
Project-URL: Github, https://github.com/playfulsparkle/pylatinize
Project-URL: Homepage, https://github.com/playfulsparkle/pylatinize
Keywords: pylatinize,ascii,alphabet,diacritics,diacritic,replace,remove,letter,accent,emoji,library,transliterate
Classifier: Development Status :: 5 - Production/Stable
Classifier: Intended Audience :: Developers
Classifier: Intended Audience :: Information Technology
Classifier: Natural Language :: English
Classifier: Operating System :: OS Independent
Classifier: Programming Language :: Python :: 3
Classifier: Programming Language :: Python :: 3.10
Classifier: Programming Language :: Python :: 3.12
Classifier: Programming Language :: Python :: 3.13
Classifier: Topic :: Software Development :: Libraries
Classifier: Topic :: Software Development :: Libraries :: Python Modules
Classifier: Topic :: Text Processing :: General
Classifier: Typing :: Typed
Classifier: Framework :: Pytest
Requires-Python: >=3.10
License-File: LICENSE
Requires-Dist: typing-extensions>=4.0.0; python_version < "3.11"
Provides-Extra: test
Requires-Dist: pytest>=8.3.0; extra == "test"
Requires-Dist: pytest-cov>=4.1.0; extra == "test"
Requires-Dist: flake8>=7.0.0; extra == "test"
Dynamic: license-file
